{
	"$type": "R5BLInventoryItem",
	"InventoryItemGppData": {
		"MaxCountInSlot": 1,
		"Weight": 1,
		"ItemTag": {
			"TagName": "EquipData.Ship.Customization.HullColor.BlackBeard.BogWood"
		},
		"ItemType": {
			"TagName": "Inventory.ItemType.Ship.Customization.HullColor"
		},
		"ActivationAbilityTag": {
			"TagName": "None"
		},
		"Attributes": [],
		"ItemMesh": "None",
		"ItemClass": 1,
		"Rarity": 4,
		"bKeepInInventoryOnDeath": true,
		"AmmoBaseParams": "None",
		"InventoryEquipment": {
			"ItemClass": "None",
			"ItemConfig": "None",
			"ItemLevel": 0,
			"SlotCountModifierParams": "None",
			"ShipItemParams": "None"
		},
		"ConsumableData": {
			"AssetPath": {
				"PackageName": "None",
				"AssetName": "None"
			}
		},
		"LootTableData": {
			"AssetPath": {
				"PackageName": "None",
				"AssetName": "None"
			}
		}
	},
	"InventoryItemUIData": {
		"ItemTexture": "None",
		"AdditionalIcons": [
			"None"
		],
		"ItemName": "Чернила осьминога",
		"ItemDescription": "Краска настолько темная и насыщенная, будто корпус был вымазан чернилами чудовищ из морских глубин.",
		"StatCurveMainStatsData": {
			"CurveTable": "None",
			"RowName": "",
			"CurveLevel": 0,
			"Stat": 0
		},
		"StatCurveSecondaryStatsData": [],
		"StatCurveAdditionalStats": [],
		"ItemDescriptionData": [],
		"EffectsDescriptions": [],
		"SetEffectsDescriptions": [],
		"Category": 1,
		"VanityText": "",
		"QualityLevel": 0,
		"MaxQualityLevel": 6,
		"SubDataId": {
			"TagName": "None"
		}
	},
	"NativeClass": "/Script/CoreUObject.Class'/Script/R5BusinessRules.R5BLInventoryItem'"
}